LICENSE
README.md
setup.py
indicators/KAMA.py
indicators/TDIGM.py
indicators/__init__.py
indicators/baseline.py
indicators/dmi_adx.py
indicators/gaussian_channel.py
indicators/mayer.py
indicators/r_macd.py
indicators/sharpe_ratio.py
indicators/spring.py
indicators/wave_trend.py
ultimate_tv_indicators.egg-info/PKG-INFO
ultimate_tv_indicators.egg-info/SOURCES.txt
ultimate_tv_indicators.egg-info/dependency_links.txt
ultimate_tv_indicators.egg-info/requires.txt
ultimate_tv_indicators.egg-info/top_level.txt